dockershield/__init__.py
dockershield/__main__.py
dockershield/arguments.py
dockershield/connection.py
dockershield/filtering.py
dockershield/interface.py
dockershield/main.py
dockershield/parser.py
dockershield/config/dockershield.yml
dockershield/systemd/dockershield.service
dockershield/systemd/systemd.py
dockershield-0.0.4.data/scripts/dockershield
dockershield-0.0.4.dist-info/METADATA
dockershield-0.0.4.dist-info/WHEEL
dockershield-0.0.4.dist-info/top_level.txt
dockershield-0.0.4.dist-info/RECORD
